scienceplots/__init__.py
scienceplots/styles/notebook.mplstyle
scienceplots/styles/scatter.mplstyle
scienceplots/styles/science.mplstyle
scienceplots/styles/color/bright.mplstyle
scienceplots/styles/color/high-contrast.mplstyle
scienceplots/styles/color/high-vis.mplstyle
scienceplots/styles/color/light.mplstyle
scienceplots/styles/color/muted.mplstyle
scienceplots/styles/color/retro.mplstyle
scienceplots/styles/color/std-colors.mplstyle
scienceplots/styles/color/vibrant.mplstyle
scienceplots/styles/journals/ieee.mplstyle
scienceplots/styles/journals/nature.mplstyle
scienceplots/styles/languages/cjk-jp-font.mplstyle
scienceplots/styles/languages/cjk-kr-font.mplstyle
scienceplots/styles/languages/cjk-sc-font.mplstyle
scienceplots/styles/languages/cjk-tc-font.mplstyle
scienceplots/styles/languages/russian-font.mplstyle
scienceplots/styles/languages/turkish-font.mplstyle
scienceplots/styles/misc/grid.mplstyle
scienceplots/styles/misc/latex-sans.mplstyle
scienceplots/styles/misc/no-latex.mplstyle
scienceplots/styles/misc/pgf.mplstyle
scienceplots/styles/misc/sans.mplstyle
SciencePlots-2.1.0.dist-info/LICENSE
SciencePlots-2.1.0.dist-info/METADATA
SciencePlots-2.1.0.dist-info/WHEEL
SciencePlots-2.1.0.dist-info/top_level.txt
SciencePlots-2.1.0.dist-info/RECORD
