Metadata-Version: 2.1
Name: SciencePlots
Version: 2.1.0
Summary: Format Matplotlib for scientific plotting
Home-page: https://github.com/garrettj403/SciencePlots/
Author: John Garrett
Author-email: garrettj403@gmail.com
Maintainer: Echedey Luis
Maintainer-email: echelual@gmail.com
License: MIT
Keywords: matplotlib-style-sheets,matplotlib-figures,scientific-papers,thesis-template,matplotlib-styles,python
Classifier: Framework :: Matplotlib
Classifier: License :: OSI Approved :: MIT License
Classifier: Programming Language :: Python :: 3
License-File: LICENSE
Requires-Dist: matplotlib
